semantic_text_splitter-0.29.0.dist-info/METADATA
semantic_text_splitter-0.29.0.dist-info/WHEEL
semantic_text_splitter/__init__.py
semantic_text_splitter/__init__.pyi
semantic_text_splitter/py.typed
semantic_text_splitter/semantic_text_splitter.abi3.so
semantic_text_splitter-0.29.0.dist-info/RECORD
