Metadata-Version: 2.4
Name: semantic-text-splitter
Version: 0.29.0
Classifier: Programming Language :: Rust
Classifier: Programming Language :: Python :: Implementation :: CPython
Classifier: Programming Language :: Python :: Implementation :: PyPy
Requires-Dist: pytest ; extra == 'test'
Requires-Dist: tokenizers ; extra == 'test'
Requires-Dist: tree-sitter-python ; extra == 'test'
Requires-Dist: pdoc ; extra == 'docs'
Provides-Extra: test
Provides-Extra: docs
Requires-Python: >=3.10
